speed_benchmark/__init__.py
speed_benchmark/speed_benchmark.py
speed_benchmark/version.py
speed_benchmark/visualization/__init__.py
speed_benchmark/visualization/generate_color.py
speed_benchmark/visualization/line_chart.py
speed_benchmark-1.1.1.dist-info/LICENSE
speed_benchmark-1.1.1.dist-info/METADATA
speed_benchmark-1.1.1.dist-info/WHEEL
speed_benchmark-1.1.1.dist-info/top_level.txt
speed_benchmark-1.1.1.dist-info/RECORD
